[
  {
    "concept": "true",
    "text": "The city of General Santos is in the Philippines."
  },
  {
    "concept": "true",
    "text": "The city of Wuzhou is in China."
  },
  {
    "concept": "true",
    "text": "The city of Yangquan is in China."
  },
  {
    "concept": "true",
    "text": "The city of Teresina is in Brazil."
  },
  {
    "concept": "true",
    "text": "The city of Pasig City is in the Philippines."
  },
  {
    "concept": "true",
    "text": "The city of Chiclayo is in Peru."
  },
  {
    "concept": "true",
    "text": "The city of Kashgar is in China."
  },
  {
    "concept": "true",
    "text": "The city of Sanmenxia is in China."
  },
  {
    "concept": "true",
    "text": "The city of Yingkou is in China."
  },
  {
    "concept": "true",
    "text": "The city of Liaocheng is in China."
  },
  {
    "concept": "true",
    "text": "The city of Hohhot is in China."
  },
  {
    "concept": "true",
    "text": "The city of Tlalpan is in Mexico."
  },
  {
    "concept": "true",
    "text": "The city of Hannover is in Germany."
  },
  {
    "concept": "true",
    "text": "The city of Cebu City is in the Philippines."
  },
  {
    "concept": "true",
    "text": "The city of Tianjin is in China."
  },
  {
    "concept": "true",
    "text": "The city of Chuzhou is in China."
  },
  {
    "concept": "true",
    "text": "The city of Shangqiu is in China."
  },
  {
    "concept": "true",
    "text": "The city of Huaibei is in China."
  },
  {
    "concept": "true",
    "text": "The city of Meizhou is in China."
  },
  {
    "concept": "true",
    "text": "The city of Orenburg is in Russia."
  },
  {
    "concept": "true",
    "text": "The city of Bien Hoa is in Vietnam."
  },
  {
    "concept": "true",
    "text": "The city of Qingdao is in China."
  },
  {
    "concept": "true",
    "text": "The city of Nuernberg is in Germany."
  },
  {
    "concept": "true",
    "text": "The city of Comilla is in Bangladesh."
  },
  {
    "concept": "true",
    "text": "The city of Barnaul is in Russia."
  },
  {
    "concept": "true",
    "text": "The city of Kaifeng is in China."
  },
  {
    "concept": "true",
    "text": "The city of Sofia is in Bulgaria."
  },
  {
    "concept": "true",
    "text": "The city of Puducherry is in India."
  },
  {
    "concept": "true",
    "text": "The city of Nouakchott is in Mauritania."
  },
  {
    "concept": "true",
    "text": "The city of Jakarta is in Indonesia."
  },
  {
    "concept": "true",
    "text": "The city of Ziyang is in China."
  },
  {
    "concept": "true",
    "text": "The city of Koeln is in Germany."
  },
  {
    "concept": "true",
    "text": "The city of Queens is in the United States."
  },
  {
    "concept": "true",
    "text": "The city of Homyel' is in Belarus."
  },
  {
    "concept": "true",
    "text": "The city of Hebi is in China."
  },
  {
    "concept": "true",
    "text": "The city of Lu'an is in China."
  },
  {
    "concept": "true",
    "text": "The city of Chaozhou is in China."
  },
  {
    "concept": "true",
    "text": "The city of Amravati is in India."
  },
  {
    "concept": "true",
    "text": "The city of Guatemala City is in Guatemala."
  },
  {
    "concept": "true",
    "text": "The city of Ho Chi Minh City is in Vietnam."
  },
  {
    "concept": "true",
    "text": "The city of Ipoh is in Malaysia."
  },
  {
    "concept": "true",
    "text": "The city of Himeji is in Japan."
  },
  {
    "concept": "true",
    "text": "The city of Huzhou is in China."
  },
  {
    "concept": "true",
    "text": "The city of Incheon is in South Korea."
  },
  {
    "concept": "true",
    "text": "The city of Pontianak is in Indonesia."
  },
  {
    "concept": "true",
    "text": "The city of Suqian is in China."
  },
  {
    "concept": "true",
    "text": "The city of Sevastopol is in Ukraine."
  },
  {
    "concept": "true",
    "text": "The city of Dhanbad is in India."
  },
  {
    "concept": "true",
    "text": "The city of Wanning is in China."
  },
  {
    "concept": "true",
    "text": "The city of Khartoum is in Sudan."
  }
]